{"days":{"_\u0004Monday":"ponedeljek","_\u0004Tuesday":"torek","_\u0004Wednesday":"sreda","_\u0004Thursday":"četrtek","_\u0004Friday":"petek","_\u0004Saturday":"sobota","_\u0004Sunday":"nedelja"},"daysShort":{"_\u0004Mon":"pon.","_\u0004Tue":"tor.","_\u0004Wed":"sre.","_\u0004Thu":"čet.","_\u0004Fri":"pet.","_\u0004Sat":"sob.","_\u0004Sun":"ned."},"months":{"_\u0004January":"januar","_\u0004February":"februar","_\u0004March":"marec","_\u0004April":"april","_\u0004May":"maj","_\u0004June":"junij","_\u0004July":"julij","_\u0004August":"avgust","_\u0004September":"september","_\u0004October":"oktober","_\u0004November":"november","_\u0004December":"december"},"monthsShort":{"_\u0004Jan":"jan.","_\u0004Feb":"feb.","_\u0004Mar":"mar.","_\u0004Apr":"apr.","_\u0004May":"maj","_\u0004Jun":"jun.","_\u0004Jul":"jul.","_\u0004Aug":"avg.","_\u0004Sep":"sep.","_\u0004Oct":"okt.","_\u0004Nov":"nov.","_\u0004Dec":"dec."}}